apexdash
