Metadata-Version: 1.1
Name: apexdash
Version: 0.0.2
Summary: Project Description
Home-page: UNKNOWN
Author: nicolas belin <nicolas@pelico.io>
Author-email: UNKNOWN
License: MIT
Platform: UNKNOWN
Classifier: Framework :: Dash
